{
  "id": 1,
  "name": "Strength & Endurance",
  "goals": [
    {
      "goal": "Warm Up",
      "bpm_low": 80,
      "bpm_high": 90,
      "rpm_low": 80,
      "rpm_high": 90,
      "rpe": 4
    },
    {
      "goal": "Seated Ride",
      "bpm_low": 100,
      "bpm_high": 120,
      "rpm_low": 100,
      "rpm_high": 120,
      "rpe": 5
    },
    {
      "goal": "Seated Climb",
      "bpm_low": 130,
      "bpm_high": 130,
      "rpm_low": 65,
      "rpm_high": 70,
      "rpe": 7
    },
    {
      "goal": "Standing Climb",
      "bpm_low": 130,
      "bpm_high": 130,
      "rpm_low": 65,
      "rpm_high": 70,
      "rpe": 8
    },
    {
      "goal": "Recovery",
      "bpm_low": 120,
      "bpm_high": 130,
      "rpm_low": 60,
      "rpm_high": 65,
      "rpe": 4
    },
    {
      "goal": "Seated Climb",
      "bpm_low": 130,
      "bpm_high": 130,
      "rpm_low": 65,
      "rpm_high": 70,
      "rpe": 8
    },
    {
      "goal": "Standing Climb",
      "bpm_low": 130,
      "bpm_high": 130,
      "rpm_low": 65,
      "rpm_high": 70,
      "rpe": 9
    },
    {
      "goal": "Seated Intervals",
      "bpm_low": 120,
      "bpm_high": 140,
      "rpm_low": 60,
      "rpm_high": 75,
      "rpe": 6
    },
    {
      "goal": "The Finish Line",
      "bpm_low": 90,
      "bpm_high": 110,
      "rpm_low": 90,
      "rpm_high": 110,
      "rpe": 5
    },
    {
      "goal": "Warm Down",
      "bpm_low": 80,
      "bpm_high": 90,
      "rpm_low": 80,
      "rpm_high": 90,
      "rpe": 1,
      "rpe_high" : 3
    }
  ]
}